{
    "Не исключено, что так сильно повлияли съемки в &amp;quot;Зачарованных&amp;quot; на Мишу...": "https://avatars.mds.yandex.net/i?id=7ff991cd63446b326ba4ad8e8531887d-5237855-images-thumbs&amp;n=13",
    "Миша Коллинз.": "https://avatars.mds.yandex.net/i?id=c32c72c7df1ad5261ca3d18d6dbc830e-3850454-images-thumbs&amp;n=13",
    "Сколько миша коллинз заработал на &amp;quot;сверхъестественном&amp;quot;? - celebri...": "https://avatars.mds.yandex.net/i?id=678310e0f445e8bbd7ab249d4072eff8-5300806-images-thumbs&amp;n=13",
    "Сколько миша коллинз заработал на &amp;quot;сверхъестественном&amp;quot;? ": "https://avatars.mds.yandex.net/i?id=cd666ddd2e09127f0e756ee4ae334055-7069324-images-thumbs&amp;n=13",
    "Миша коллинз: биография, фильмография и личная жизнь.": "https://avatars.mds.yandex.net/i?id=baa0f0a533e4e7a083fc7a31fe04ee32-4979110-images-thumbs&amp;n=13",
    "Миша Коллинз фото.": "https://avatars.mds.yandex.net/i?id=cccb972c29fbc2e0158231bb599e480e-5276461-images-thumbs&amp;n=13",
    "Фото: Миша Коллинз (1974) #2233295.": "https://avatars.mds.yandex.net/i?id=0b210a331792d332d264c16dd183cf97-7045415-images-thumbs&amp;n=13",
    "Миша пишет. ": "https://avatars.mds.yandex.net/i?id=3639841aa09eb72bafe2a573bcf065c7-4570996-images-thumbs&amp;n=13",
    "Актер миша коллинз и сериал с мистическим названием &amp;quot;зачарованные&amp;quot...": "https://avatars.mds.yandex.net/i?id=5e7047624f1c1a98d64c89dfd0c99477-4591508-images-thumbs&amp;n=13",
    "Irudia ": "https://avatars.mds.yandex.net/i?id=af3d0593bd0807c5825bfa635fb27ec4-5243680-images-thumbs&amp;n=13",
    "...любимому нами сверхъестественному ангелу Касу Мише Коллинзу https... ": "https://avatars.mds.yandex.net/i?id=b008d816decab46750902f68f5bf313f-2982957-images-thumbs&amp;n=13",
    "Сверхъестественное, Миша Коллинз, ЖИВА, Случайные действия.": "https://avatars.mds.yandex.net/i?id=11c4ad05786a36815b4fdc07149770b8-5555892-images-thumbs&amp;n=13",
    "Миша коллинз сверхъестественное wiki fandom.": "https://avatars.mds.yandex.net/i?id=9e81eb19edb4dd3da909897b16d07f20-5277125-images-thumbs&amp;n=13",
    "...в которых за весь период своей фильмографии отметился Миша. ": "https://avatars.mds.yandex.net/i?id=69e06f48b53e06379cafb54ec8ecf5fa-5434889-images-thumbs&amp;n=13",
    "Миша коллинз обои на рабочий стол.": "https://avatars.mds.yandex.net/i?id=1519d1e56df398a7e623e8864b9093ed-4477047-images-thumbs&amp;n=13",
    "Миша Коллинз в сериале &amp;quot;Reinventing the Wheelers&amp;quot; .": "https://avatars.mds.yandex.net/i?id=9992d9619cb02f1eb26ec5602218c59d-4507854-images-thumbs&amp;n=13",
    "Миша Коллинз (33 фото) .": "https://avatars.mds.yandex.net/i?id=47a7a98a2db7c2c91fa26894cc68e2da-5528595-images-thumbs&amp;n=13",
    "Миша коллинз - биография, личная жизнь, фото, новости, жена, разводится...": "https://avatars.mds.yandex.net/i?id=d274cc72ae40de30140892decee4c72f-5233063-images-thumbs&amp;n=13",
    "Пин от пользователя Βιργινια Αχιλλακη на доске Supernatural Миша коллинз...": "https://avatars.mds.yandex.net/i?id=ddb926a786d05bdc8d2c45d66ba9f257-5087064-images-thumbs&amp;n=13",
    "Миша коллинз биография личная жизнь и фильмография.": "https://avatars.mds.yandex.net/i?id=5c2c70a38ac0e609f98fc3ee892971d1-5284035-images-thumbs&amp;n=13",
    "Фаны Миша Коллинз. ": "https://avatars.mds.yandex.net/i?id=239e41d69f0e79c50df04e2ccb325b85-4971670-images-thumbs&amp;n=13",
    "Миша и Саша Коллинз - кто более успешен? | ": "https://avatars.mds.yandex.net/i?id=518f43fa99208af90b990e590c40030e-5220716-images-thumbs&amp;n=13",
    "angie 🇺 🇦 en Twitter: &amp;quot;25. миша коллинз.": "https://avatars.mds.yandex.net/i?id=e739e26417dd4d42c34bb79583bde8f9-4145875-images-thumbs&amp;n=13",
    "31. Миша Коллинз. ": "https://avatars.mds.yandex.net/i?id=8cd0c7424cc0bfc6c044be815691a78e-5341307-images-thumbs&amp;n=13",
    "Миша Most.": "https://avatars.mds.yandex.net/i?id=45ad3d802d63bd505b5569c27e41c051-5234982-images-thumbs&amp;n=13",
    "Миша, 32, Краснодар.": "https://avatars.mds.yandex.net/i?id=2a0000018393118f8491d9b050a8d4e4fdcf-1609306-fast-images&amp;n=13",
    "Миша Смирнов. ": "https://avatars.mds.yandex.net/i?id=7d4ad6d097af9c2efb236710a21e72b2-4823985-images-thumbs&amp;n=13",
    "Миша коллинз.": "https://avatars.mds.yandex.net/i?id=47e26268aa1bfde494c179977e8aaa0c-5340565-images-thumbs&amp;n=13"
}